vaibhavpackage/__init__.py
vaibhavpackage-0.3.dist-info/METADATA
vaibhavpackage-0.3.dist-info/WHEEL
vaibhavpackage-0.3.dist-info/top_level.txt
vaibhavpackage-0.3.dist-info/RECORD
