Metadata-Version: 2.1
Name: vaibhavpackage
Version: 0.3
Summary: This is code made by Vaibhav Verma.
Author: Vaibhav
